weyland/__init__.py
weyland/languages.py
weyland/lexer.py
weyland-0.2.6.dist-info/LICENSE
weyland-0.2.6.dist-info/METADATA
weyland-0.2.6.dist-info/WHEEL
weyland-0.2.6.dist-info/top_level.txt
weyland-0.2.6.dist-info/RECORD
