Metadata-Version: 2.1
Name: weyland
Version: 0.2.6
Summary: An alternative way to write regular expression and a lexer using them.
Home-page: https://github.com/Xitog/weyland
Author: Damien Gouteux
Author-email: damien.gouteux@gmail.com
Maintainer: Damien Gouteux
Maintainer-email: damien.gouteux@gmail.com
License: MIT
Keywords: weyland,lexer,regular expression,regex,text,languages
Platform: UNKNOWN
Classifier: Development Status :: 3 - Alpha
Classifier: License :: OSI Approved :: MIT License
Classifier: Operating System :: OS Independent
Classifier: Programming Language :: Python
Classifier: Programming Language :: Python :: 3 :: Only
Classifier: Programming Language :: Python :: Implementation :: CPython
Classifier: Topic :: Software Development :: Libraries :: Python Modules
Classifier: Topic :: Software Development :: Documentation
Classifier: Topic :: Text Processing
Classifier: Programming Language :: Other
Requires-Python: >=3.5
